exceptions_hog/__init__.py
exceptions_hog/exceptions.py
exceptions_hog/handler.py
exceptions_hog/settings.py
exceptions_hog/utils.py
exceptions_hog/version.py
drf_exceptions_hog-0.4.0.dist-info/LICENSE
drf_exceptions_hog-0.4.0.dist-info/METADATA
drf_exceptions_hog-0.4.0.dist-info/WHEEL
drf_exceptions_hog-0.4.0.dist-info/top_level.txt
drf_exceptions_hog-0.4.0.dist-info/RECORD
