Metadata-Version: 2.1
Name: drf-exceptions-hog
Version: 0.4.0
Summary: Standardized and easy-to-parse API error responses for DRF.
Home-page: https://github.com/posthog/drf-exceptions-hog
Author: PostHog
Author-email: hey@posthog.com
Classifier: Programming Language :: Python :: 3
Classifier: Programming Language :: Python :: 3.7
Classifier: Programming Language :: Python :: 3.8
Classifier: Programming Language :: Python :: 3.9
Classifier: License :: OSI Approved :: MIT License
Classifier: Operating System :: OS Independent
Requires-Python: >=3.7
License-File: LICENSE
